uld/__init__.py
uld/__main__.py
uld/cli.py
uld/config.py
uld/detector.py
uld/exceptions.py
uld/models.py
uld/progress.py
uld/engines/__init__.py
uld/engines/base.py
uld/engines/http.py
uld/engines/torrent.py
uld/engines/video.py
uld_cli-1.1.2.dist-info/METADATA
uld_cli-1.1.2.dist-info/WHEEL
uld_cli-1.1.2.dist-info/entry_points.txt
uld_cli-1.1.2.dist-info/licenses/LICENSE
uld_cli-1.1.2.dist-info/RECORD
