Metadata-Version: 2.4
Name: uld-cli
Version: 1.1.2
Summary: Unified Local Downloader - A single CLI for torrents, magnet links, videos, and direct downloads
Project-URL: Homepage, https://github.com/jd-co/uld
Project-URL: Repository, https://github.com/jd-co/uld
Project-URL: Issues, https://github.com/jd-co/uld/issues
Author: Sheik Javeed
License-Expression: MIT
License-File: LICENSE
Keywords: cli,command-line-tool,curl,download,download-manager,downloader,http,libtorrent,magnet,playlist,python-cli,torrent,video-downloader,wget,youtube,yt-dlp
Classifier: Development Status :: 5 - Production/Stable
Classifier: Environment :: Console
Classifier: Intended Audience :: Developers
Classifier: Intended Audience :: End Users/Desktop
Classifier: License :: OSI Approved :: MIT License
Classifier: Operating System :: OS Independent
Classifier: Programming Language :: Python :: 3
Classifier: Programming Language :: Python :: 3.10
Classifier: Programming Language :: Python :: 3.11
Classifier: Programming Language :: Python :: 3.12
Classifier: Topic :: Internet
Classifier: Topic :: Utilities
Requires-Python: >=3.10
Requires-Dist: httpx>=0.28.1
Requires-Dist: libtorrent-windows-dll>=0.0.3; sys_platform == 'win32'
Requires-Dist: libtorrent>=2.0.11
Requires-Dist: pydantic-settings>=2.0.0
Requires-Dist: pydantic>=2.0.0
Requires-Dist: rich>=13.0.0
Requires-Dist: typer>=0.9.0
Requires-Dist: yt-dlp>=2024.0.0
Provides-Extra: dev
Requires-Dist: mypy>=1.19.1; extra == 'dev'
Requires-Dist: pre-commit>=4.5.1; extra == 'dev'
Requires-Dist: pytest-asyncio>=1.3.0; extra == 'dev'
Requires-Dist: pytest-cov>=7.0.0; extra == 'dev'
Requires-Dist: pytest>=9.0.2; extra == 'dev'
Requires-Dist: ruff>=0.14.10; extra == 'dev'
